openSIMS/__init__.py
openSIMS/API/Calibration.py
openSIMS/API/Cameca.py
openSIMS/API/Ellipse.py
openSIMS/API/Geochron.py
openSIMS/API/PbPb.py
openSIMS/API/Process.py
openSIMS/API/SHRIMP.py
openSIMS/API/Sample.py
openSIMS/API/Settings.py
openSIMS/API/Simplex.py
openSIMS/API/Stable.py
openSIMS/API/Toolbox.py
openSIMS/GUI/Doc.py
openSIMS/GUI/Export.py
openSIMS/GUI/List.py
openSIMS/GUI/Log.py
openSIMS/GUI/Main.py
openSIMS/GUI/Method.py
openSIMS/GUI/Open.py
openSIMS/GUI/Plot.py
openSIMS/GUI/View.py
openSIMS/GUI/__init__.py
openSIMS/Methods/__init__.py
openSIMS/Methods/Exporters/Pb-Pb.py
openSIMS/Methods/Exporters/Th-Pb.py
openSIMS/Methods/Exporters/U-Pb-Pb.py
openSIMS/Methods/Exporters/U-Pb.py
openSIMS/Methods/Exporters/__init__.py
openSIMS/Methods/Exporters/default.py
openSIMS/Methods/csv/O.csv
openSIMS/Methods/csv/Pb-Pb.csv
openSIMS/Methods/csv/S.csv
openSIMS/Methods/csv/Th-Pb.csv
openSIMS/Methods/csv/U-Pb.csv
openSIMS/Methods/json/O.json
openSIMS/Methods/json/Pb-Pb.json
openSIMS/Methods/json/S.json
openSIMS/Methods/json/Th-Pb.json
openSIMS/Methods/json/U-Pb.json
openSIMS-0.7.1.dist-info/LICENSE
openSIMS-0.7.1.dist-info/METADATA
openSIMS-0.7.1.dist-info/WHEEL
openSIMS-0.7.1.dist-info/top_level.txt
openSIMS-0.7.1.dist-info/RECORD
