Metadata-Version: 2.1
Name: openSIMS
Version: 0.7.1
Summary: A Python package for SIMS data reduction
Author-email: Pieter Vermeesch <p.vermeesch@ucl.ac.uk>
Project-URL: Homepage, https://github.com/pvermees/openSIMS
Project-URL: Issues, https://github.com/pvermees/openSIMS/issues
Classifier: Programming Language :: Python :: 3
Classifier: License :: OSI Approved :: GNU Lesser General Public License v3 (LGPLv3)
Classifier: Operating System :: OS Independent
Requires-Python: >=3.8
License-File: LICENSE
Requires-Dist: numpy
Requires-Dist: pandas
Requires-Dist: scipy
Requires-Dist: matplotlib
